splitp/__init__.py
splitp/alignment.py
splitp/constants.py
splitp/constructions.py
splitp/enums.py
splitp/matrix.py
splitp/model.py
splitp/phylogenetics.py
splitp/phylogeny.py
splitp/simulation.py
splitp/splits.py
splitp/squangles.py
splitp/trees.py
splitp/parsers/__init__.py
splitp/parsers/fasta.py
splitp/parsers/newick.py
splitp/polynomials/sqg1.txt
splitp/polynomials/sqg2.txt
splitp/polynomials/sqg3.txt
splitp-0.3.2.dist-info/licenses/LICENSE
splitp-0.3.2.dist-info/METADATA
splitp-0.3.2.dist-info/WHEEL
splitp-0.3.2.dist-info/top_level.txt
splitp-0.3.2.dist-info/RECORD
