Metadata-Version: 2.4
Name: splitp
Version: 0.3.2
Summary: Phylogenetic tools and methods involving splits and matrix rank
Home-page: https://github.com/js51/SplitP
Author: Joshua Stevenson
Author-email: joshua.stevenson@utas.edu.au
Classifier: Programming Language :: Python :: 3
Classifier: License :: OSI Approved :: MIT License
Classifier: Operating System :: OS Independent
Requires-Python: >=3.6
License-File: LICENSE
Dynamic: author
Dynamic: author-email
Dynamic: classifier
Dynamic: description
Dynamic: description-content-type
Dynamic: home-page
Dynamic: license-file
Dynamic: requires-python
Dynamic: summary
